{"expireTime":9007200834986050000,"key":"transformer-remark-markdown-html-ast-63821a8e49d3673ea821138932edf113-gatsby-remark-relative-imagesgatsby-remark-imagesgatsby-remark-copy-linked-filesgatsby-remark-prismjs-","val":{"type":"root","children":[{"type":"element","tagName":"p","properties":{},"children":[{"type":"text","value":"Are you thinking about finishing your basement, or remodelling your kitchen or bathroom?","position":{"start":{"line":1,"column":1,"offset":0},"end":{"line":1,"column":89,"offset":88}}}],"position":{"start":{"line":1,"column":1,"offset":0},"end":{"line":1,"column":89,"offset":88}}},{"type":"text","value":"\n"},{"type":"element","tagName":"p","properties":{},"children":[{"type":"text","value":"If you're thinking about renovations, then you are probably already thinking about one of your biggest hurdles ","position":{"start":{"line":3,"column":1,"offset":90},"end":{"line":3,"column":112,"offset":201}}}],"position":{"start":{"line":3,"column":1,"offset":90},"end":{"line":3,"column":112,"offset":201}}},{"type":"text","value":"\n"},{"type":"element","tagName":"h2","properties":{},"children":[{"type":"text","value":"Why Choose Trim Tile and Stone?","position":{"start":{"line":5,"column":4,"offset":206},"end":{"line":5,"column":35,"offset":237}}}],"position":{"start":{"line":5,"column":1,"offset":203},"end":{"line":5,"column":35,"offset":237}}},{"type":"text","value":"\n"},{"type":"element","tagName":"p","properties":{},"children":[{"type":"text","value":"Differentiator","position":{"start":{"line":7,"column":1,"offset":239},"end":{"line":7,"column":15,"offset":253}}}],"position":{"start":{"line":7,"column":1,"offset":239},"end":{"line":7,"column":15,"offset":253}}},{"type":"text","value":"\n"},{"type":"element","tagName":"h2","properties":{},"children":[{"type":"text","value":"Our Story","position":{"start":{"line":9,"column":4,"offset":258},"end":{"line":9,"column":13,"offset":267}}}],"position":{"start":{"line":9,"column":1,"offset":255},"end":{"line":9,"column":13,"offset":267}}},{"type":"text","value":"\n"},{"type":"element","tagName":"p","properties":{},"children":[{"type":"text","value":"Story","position":{"start":{"line":11,"column":1,"offset":269},"end":{"line":11,"column":6,"offset":274}}}],"position":{"start":{"line":11,"column":1,"offset":269},"end":{"line":11,"column":6,"offset":274}}},{"type":"text","value":"\n"},{"type":"element","tagName":"h2","properties":{},"children":[{"type":"text","value":"Offerings","position":{"start":{"line":13,"column":4,"offset":279},"end":{"line":13,"column":13,"offset":288}}}],"position":{"start":{"line":13,"column":1,"offset":276},"end":{"line":13,"column":13,"offset":288}}},{"type":"text","value":"\n"},{"type":"element","tagName":"p","properties":{},"children":[{"type":"text","value":"offerings","position":{"start":{"line":15,"column":1,"offset":290},"end":{"line":15,"column":10,"offset":299}}}],"position":{"start":{"line":15,"column":1,"offset":290},"end":{"line":15,"column":10,"offset":299}}},{"type":"text","value":"\n"},{"type":"element","tagName":"h2","properties":{},"children":[{"type":"text","value":"CTA section","position":{"start":{"line":17,"column":4,"offset":304},"end":{"line":17,"column":15,"offset":315}}}],"position":{"start":{"line":17,"column":1,"offset":301},"end":{"line":17,"column":15,"offset":315}}},{"type":"text","value":"\n"},{"type":"element","tagName":"p","properties":{},"children":[{"type":"text","value":"Inquiry / estimate","position":{"start":{"line":19,"column":1,"offset":317},"end":{"line":19,"column":19,"offset":335}}}],"position":{"start":{"line":19,"column":1,"offset":317},"end":{"line":19,"column":19,"offset":335}}}],"position":{"start":{"line":1,"column":1,"offset":0},"end":{"line":19,"column":19,"offset":335}}}}